{
  "output_model_file": "./surface.mat",
  "wavelength_file":   "./wavelengths.txt",
  "normalize":"Euclidean",
  "reference_windows":[[400,1250],[1450,1750],[2050,2450]],
  "sources":
    [
      {
        "input_spectrum_files":
          [
            "filtered_other"
          ],
        "n_components": 1,
        "windows": [
          {
            "interval":[300,785],
            "regularizer":10,
            "correlation":"decorrelated"
          },
          {
            "interval":[785,1250],
            "regularizer":1e-6,
            "correlation":"EM"
          },
          {
            "interval":[1250,2500],
            "regularizer":10,
            "correlation":"decorrelated"
          }
        ]
      },
      {
        "input_spectrum_files":
          [
            "filtered_veg"
          ],
        "n_components": 1,
        "windows": [
          {
            "interval":[300,350],
            "regularizer":10,
            "correlation":"decorrelated"
          },
          {
            "interval":[350,480],
            "regularizer":1e-6,
            "correlation":"EM"
          },
          {
            "interval":[480,785],
            "regularizer":10,
            "correlation":"decorrelated"
          },
          {
            "interval":[785,1250],
            "regularizer":1e-6,
            "correlation":"EM"
          },
          {
            "interval":[1250,2500],
            "regularizer":10,
            "correlation":"decorrelated"
          }
        ]
      },
      {
        "input_spectrum_files":
          [
            "filtered_ocean"
          ],
        "n_components": 1,
        "windows": [
          {
            "interval":[300,880],
            "regularizer":10,
            "correlation":"decorrelated"
          },
          {
            "interval":[880,1250],
            "regularizer":1e-6,
            "correlation":"EM"
          },
          {
            "interval":[1250,2500],
            "regularizer":10,
            "correlation":"decorrelated"
          }
        ]
      },
      {
        "input_spectrum_files":
          [
            "surface_Liquids"
          ],
        "n_components": 2,
        "windows": [
          {
            "interval":[300,880],
            "regularizer":10,
            "correlation":"decorrelated"
          },
          {
            "interval":[880,1250],
            "regularizer":1e-6,
            "correlation":"EM"
          },
          {
            "interval":[1250,2500],
            "regularizer":10,
            "correlation":"decorrelated"
          }
        ]
      }
  ]
}
